{
	"final_sequence": [0],
	"videos": [
		{
			"name": "test/destra1_speedup.mp4",
			"background": "test/empty.png",
			"input": ["test/destra1.mp4"],
			"transformations": [[
				{
					"operation": "SPEEDUP",
					"parameters": "0.1*PTS"
				}]
			]
		},
		{
			"name": "test/sinistra1_speedup.mp4",
			"background": "test/empty.png",
			"input": ["test/sinistra1.mp4"],
			"transformations": [[
				{
					"operation": "SPEEDUP",
					"parameters": "0.1*PTS"
				}]
			]
		},
		{
			"name": "test/destra1esinistra1.mp4", 
			"background": "test/empty.png",
			"input": ["test/sinistra1_speedup.mp4",
					  "test/destra1_speedup.mp4"],
			"transformations": [
			[
				{
					"operation": "POSITION",
					"parameters": "0:218.5"
				}
			],
			[
				{
					"operation": "POSITION",
					"parameters": "800:218.5"
				}
			]]
		}
	]
}
